[
 {
  "text": "Unsure",
  "voice": "arthur",
  "file": "a16_unsure.mp3"
 },
 {
  "text": "Guess",
  "voice": "arthur",
  "file": "a16_guess.mp3"
 },
 {
  "text": "Estimate",
  "voice": "arthur",
  "file": "a16_estimate.mp3"
 },
 {
  "text": "Roughly",
  "voice": "arthur",
  "file": "a16_roughly.mp3"
 },
 {
  "text": "Approximately",
  "voice": "arthur",
  "file": "a16_approximately.mp3"
 },
 {
  "text": "Figure out",
  "voice": "arthur",
  "file": "a16_figure_out.mp3"
 },
 {
  "text": "Vague",
  "voice": "arthur",
  "file": "a16_vague.mp3"
 },
 {
  "text": "Frankly",
  "voice": "arthur",
  "file": "a16_frankly.mp3"
 },
 {
  "text": "It is useful, isn&#39;t it?",
  "voice": "ellen",
  "file": "a16_it_is_useful_isn_39_t_it.mp3"
 },
 {
  "text": "You can confirm it later, can&#39;t you?",
  "voice": "arthur",
  "file": "a16_you_can_confirm_it_later_can_39_t_you.mp3"
 },
 {
  "text": "You don&#39;t have the figure, do you?",
  "voice": "ellen",
  "file": "a16_you_don_39_t_have_the_figure_do_you.mp3"
 },
 {
  "text": "We have met before, haven&#39;t we?",
  "voice": "arthur",
  "file": "a16_we_have_met_before_haven_39_t_we.mp3"
 },
 {
  "text": "Vanessa, what are the exact numbers for this quarter?",
  "voice": "arthur",
  "file": "a16_vanessa_what_are_the_exact_numbers_for_this_quar.mp3"
 },
 {
  "text": "That&#39;s a fair question. Let me think for a second.",
  "voice": "ellen",
  "file": "a16_that_39_s_a_fair_question_let_me_think_for_a_sec.mp3"
 },
 {
  "text": "Take your time. You have a rough idea, don&#39;t you?",
  "voice": "arthur",
  "file": "a16_take_your_time_you_have_a_rough_idea_don_39_t_yo.mp3"
 },
 {
  "text": "Honestly, I&#39;m unsure of the exact figure, but roughly it&#39;s around forty thousand.",
  "voice": "ellen",
  "file": "a16_honestly_i_39_m_unsure_of_the_exact_figure_but_r.mp3"
 },
 {
  "text": "And the growth? We&#39;re up a little, aren&#39;t we?",
  "voice": "arthur",
  "file": "a16_and_the_growth_we_39_re_up_a_little_aren_39_t_we.mp3"
 },
 {
  "text": "Yes. I&#39;d estimate we&#39;re up about ten percent. Frankly, I only have a vague picture right now.",
  "voice": "ellen",
  "file": "a16_yes_i_39_d_estimate_we_39_re_up_about_ten_percen.mp3"
 },
 {
  "text": "That&#39;s fine for now. You&#39;ll send the exact numbers later, won&#39;t you?",
  "voice": "arthur",
  "file": "a16_that_39_s_fine_for_now_you_39_ll_send_the_exact.mp3"
 },
 {
  "text": "Of course. Let me figure out the precise total and get back to you this afternoon.",
  "voice": "ellen",
  "file": "a16_of_course_let_me_figure_out_the_precise_total_an.mp3"
 },
 {
  "text": "That&#39;s a good question. Let me think for a second.",
  "voice": "ellen",
  "file": "a16_that_39_s_a_good_question_let_me_think_for_a_sec.mp3"
 },
 {
  "text": "Honestly, I&#39;m unsure, but roughly it&#39;s around twenty.",
  "voice": "arthur",
  "file": "a16_honestly_i_39_m_unsure_but_roughly_it_39_s_aroun.mp3"
 },
 {
  "text": "I&#39;d estimate we&#39;re up approximately ten percent.",
  "voice": "ellen",
  "file": "a16_i_39_d_estimate_we_39_re_up_approximately_ten_pe.mp3"
 },
 {
  "text": "Let me figure it out and get back to you.",
  "voice": "arthur",
  "file": "a16_let_me_figure_it_out_and_get_back_to_you.mp3"
 },
 {
  "text": "We can confirm the details later, can&#39;t we?",
  "voice": "ellen",
  "file": "a16_we_can_confirm_the_details_later_can_39_t_we.mp3"
 },
 {
  "text": "I want to be honest with you about something. For years, when someone asked me a hard question in English, I just froze. My mind went blank, and the silence felt huge. I thought I had to answer perfectly and instantly, so when I could not, I panicked. Then a teacher told me something simple that changed everything. She said: you do not have to be fast, you have to stay calm. Buy yourself a little time. So now, when I am unsure, I do not freeze. I say, that is a good question, let me think for a second. Or, honestly, I am not sure, but I would guess it is around twenty. Frankly, those small phrases are not weak. They are confident. They tell the other person, I am thinking, please wait. And here is the trick I love the most. When I want to keep the conversation soft and friendly, I add a little question tag at the end. It is useful, isn't it? You have felt this too, haven't you? That tiny tag invites the other person in, and suddenly I am not alone with the pressure. The conversation breathes.",
  "voice": "ellen",
  "file": "a16_listening_thinking_out_loud.mp3"
 },
 {
  "text": "Let me tell you about a moment in a meeting last month. My manager turned to me and asked, so what are the exact numbers for this quarter? Everyone was looking at me, and I did not have the precise figure in my head. A year ago, I would have panicked. This time, I stayed calm. I said, that is a fair question. Let me think for a second. Then I gave a vague but honest answer. I said, I do not have the exact number in front of me, but roughly, it is around forty thousand. I would estimate we are up about ten percent. Then I added a tag to check we were on the same page. We can confirm the details later, can't we? My manager nodded. Here is what I learned. Nobody expects you to know everything instantly. What they respect is someone who stays calm, gives an honest estimate, and is not afraid to say, I will get back to you with the exact figure. Buying time is not a weakness. Frankly, it is a sign of a confident professional.",
  "voice": "arthur",
  "file": "a16_listening_a_meeting_moment.mp3"
 },
 {
  "text": "First, when I do not know the answer right away, I stay calm instead of freezing. Then I buy a little time and say, that is a good question, let me think for a second. After that, I give an honest answer and admit I am unsure: honestly, I am not sure, but roughly it is around twenty. Next, I soften it and check with a question tag, so it is about twenty, isn't it? In the end, if I really do not know, I promise to follow up and say, I will get back to you with the exact figure.",
  "voice": "arthur",
  "file": "pc16_order_l16.mp3"
 },
 {
  "text": "Unsure",
  "voice": "arthur",
  "file": "pc16_unsure.mp3"
 },
 {
  "text": "Guess",
  "voice": "arthur",
  "file": "pc16_guess.mp3"
 },
 {
  "text": "Estimate",
  "voice": "arthur",
  "file": "pc16_estimate.mp3"
 },
 {
  "text": "Roughly",
  "voice": "arthur",
  "file": "pc16_roughly.mp3"
 },
 {
  "text": "Approximately",
  "voice": "arthur",
  "file": "pc16_approximately.mp3"
 },
 {
  "text": "Figure out",
  "voice": "arthur",
  "file": "pc16_figure_out.mp3"
 },
 {
  "text": "Vague",
  "voice": "arthur",
  "file": "pc16_vague.mp3"
 },
 {
  "text": "Frankly",
  "voice": "arthur",
  "file": "pc16_frankly.mp3"
 },
 {
  "text": "That&#39;s a fair question, isn&#39;t it?",
  "voice": "ellen",
  "file": "pc16_that_39_s_a_fair_question_isn_39_t_it.mp3"
 },
 {
  "text": "Honestly, I&#39;m unsure of the exact figure.",
  "voice": "arthur",
  "file": "pc16_honestly_i_39_m_unsure_of_the_exact_figure.mp3"
 },
 {
  "text": "Roughly, it&#39;s around forty thousand.",
  "voice": "ellen",
  "file": "pc16_roughly_it_39_s_around_forty_thousand.mp3"
 },
 {
  "text": "I&#39;d estimate we&#39;re up about ten percent.",
  "voice": "arthur",
  "file": "pc16_i_39_d_estimate_we_39_re_up_about_ten_percent.mp3"
 },
 {
  "text": "You&#39;ll send the exact numbers, won&#39;t you?",
  "voice": "ellen",
  "file": "pc16_you_39_ll_send_the_exact_numbers_won_39_t_you.mp3"
 },
 {
  "text": "Let me figure out the total and get back to you.",
  "voice": "arthur",
  "file": "pc16_let_me_figure_out_the_total_and_get_back_to_you.mp3"
 },
 {
  "text": "That's a good question. Let me think for a second.",
  "voice": "ellen",
  "file": "pc16_that_s_a_good_question_let_me_think_for_a_second.mp3"
 },
 {
  "text": "Honestly, I'm unsure, but roughly it's around twenty.",
  "voice": "arthur",
  "file": "pc16_honestly_i_m_unsure_but_roughly_it_s_around_twen.mp3"
 },
 {
  "text": "I'd estimate we're up approximately ten percent.",
  "voice": "ellen",
  "file": "pc16_i_d_estimate_we_re_up_approximately_ten_percent.mp3"
 },
 {
  "text": "Let me figure it out and get back to you.",
  "voice": "arthur",
  "file": "pc16_let_me_figure_it_out_and_get_back_to_you.mp3"
 },
 {
  "text": "We can confirm the details later, can't we?",
  "voice": "ellen",
  "file": "pc16_we_can_confirm_the_details_later_can_t_we.mp3"
 },
 {
  "text": "That&#39;s a good question. Let me think for a second.",
  "voice": "arthur",
  "file": "pc16_that_39_s_a_good_question_let_me_think_for_a_sec.mp3"
 },
 {
  "text": "Honestly, I&#39;m unsure, but roughly it&#39;s around twenty.",
  "voice": "ellen",
  "file": "pc16_honestly_i_39_m_unsure_but_roughly_it_39_s_aroun.mp3"
 },
 {
  "text": "I&#39;d estimate we&#39;re up approximately ten percent.",
  "voice": "arthur",
  "file": "pc16_i_39_d_estimate_we_39_re_up_approximately_ten_pe.mp3"
 },
 {
  "text": "We can confirm the details later, can&#39;t we?",
  "voice": "ellen",
  "file": "pc16_we_can_confirm_the_details_later_can_39_t_we.mp3"
 }
]