[
 {
  "text": "Rephrase",
  "voice": "arthur",
  "file": "a7_rephrase.mp3"
 },
 {
  "text": "In other words",
  "voice": "ellen",
  "file": "a7_in_other_words.mp3"
 },
 {
  "text": "Buy time",
  "voice": "arthur",
  "file": "a7_buy_time.mp3"
 },
 {
  "text": "Roughly",
  "voice": "arthur",
  "file": "a7_roughly.mp3"
 },
 {
  "text": "To be honest",
  "voice": "arthur",
  "file": "a7_to_be_honest.mp3"
 },
 {
  "text": "Bear with me",
  "voice": "ellen",
  "file": "a7_bear_with_me.mp3"
 },
 {
  "text": "Touch on",
  "voice": "arthur",
  "file": "a7_touch_on.mp3"
 },
 {
  "text": "Get back to you",
  "voice": "arthur",
  "file": "a7_get_back_to_you.mp3"
 },
 {
  "text": "Put it simply",
  "voice": "ellen",
  "file": "a7_put_it_simply.mp3"
 },
 {
  "text": "Depend",
  "voice": "arthur",
  "file": "a7_depend.mp3"
 },
 {
  "text": "That is a great question. Let me think for a second.",
  "voice": "arthur",
  "file": "a7_that_is_a_great_question_let_me_think_for_a_seco.mp3"
 },
 {
  "text": "In other words, we choose the safer value.",
  "voice": "ellen",
  "file": "a7_in_other_words_we_choose_the_safer_value.mp3"
 },
 {
  "text": "To be honest, the answer depends on the market.",
  "voice": "arthur",
  "file": "a7_to_be_honest_the_answer_depends_on_the_market.mp3"
 },
 {
  "text": "Let me check and get back to you on that.",
  "voice": "ellen",
  "file": "a7_let_me_check_and_get_back_to_you_on_that.mp3"
 },
 {
  "text": "Marcos, how do you make sure a valuation is fair when the market is so unstable?",
  "voice": "ellen",
  "file": "a7_marcos_how_do_you_make_sure_a_valuation_is_fair.mp3"
 },
 {
  "text": "I see. Could you explain how exactly?",
  "voice": "ellen",
  "file": "a7_i_see_could_you_explain_how_exactly.mp3"
 },
 {
  "text": "To put it simply, when prices are unstable, we choose the safer value. In other words, we stay conservative.",
  "voice": "arthur",
  "file": "a7_to_put_it_simply_when_prices_are_unstable_we_cho.mp3"
 },
 {
  "text": "And how long does the whole process take, roughly?",
  "voice": "ellen",
  "file": "a7_and_how_long_does_the_whole_process_take_roughly.mp3"
 },
 {
  "text": "Roughly two weeks. I touched on the timeline earlier, but bear with me if you want the exact figure.",
  "voice": "arthur",
  "file": "a7_roughly_two_weeks_i_touched_on_the_timeline_earl.mp3"
 },
 {
  "text": "No need. One last thing -- what is the exact margin of error?",
  "voice": "ellen",
  "file": "a7_no_need_one_last_thing_what_is_the_exact_margin.mp3"
 },
 {
  "text": "I do not have that number with me right now. Let me check and get back to you on that.",
  "voice": "arthur",
  "file": "a7_i_do_not_have_that_number_with_me_right_now_let.mp3"
 },
 {
  "text": "To put it simply, we find a fair price.",
  "voice": "arthur",
  "file": "a7_to_put_it_simply_we_find_a_fair_price.mp3"
 },
 {
  "text": "To be honest, it depends on the market.",
  "voice": "ellen",
  "file": "a7_to_be_honest_it_depends_on_the_market.mp3"
 },
 {
  "text": "Roughly two weeks, but bear with me.",
  "voice": "arthur",
  "file": "a7_roughly_two_weeks_but_bear_with_me.mp3"
 },
 {
  "text": "Answering tough questions is a skill, and like any skill, you can learn it. Here are my three best tips. First, stay calm and buy yourself a few seconds. A simple opener like, that is a great question, gives your brain time to organize the answer. Second, be honest. If you do not know something, never guess a number. Just say you will get back to the person with the exact figure. Honesty builds trust far more than a wrong answer. And third, when your answer is complex, paraphrase it. Use a phrase like, in other words, or, to put it simply, and then give a short, clear version. Remember: a calm, honest, simple answer is always stronger than a fast, nervous one. Take your time, and you will do great.",
  "voice": "ellen",
  "file": "a7_listening_pressure.mp3"
 },
 {
  "text": "Rephrase",
  "voice": "arthur",
  "file": "pc7_rephrase.mp3"
 },
 {
  "text": "In other words",
  "voice": "ellen",
  "file": "pc7_in_other_words.mp3"
 },
 {
  "text": "Buy time",
  "voice": "arthur",
  "file": "pc7_buy_time.mp3"
 },
 {
  "text": "Roughly",
  "voice": "arthur",
  "file": "pc7_roughly.mp3"
 },
 {
  "text": "To be honest",
  "voice": "arthur",
  "file": "pc7_to_be_honest.mp3"
 },
 {
  "text": "Bear with me",
  "voice": "ellen",
  "file": "pc7_bear_with_me.mp3"
 },
 {
  "text": "Touch on",
  "voice": "arthur",
  "file": "pc7_touch_on.mp3"
 },
 {
  "text": "Get back to you",
  "voice": "arthur",
  "file": "pc7_get_back_to_you.mp3"
 },
 {
  "text": "Put it simply",
  "voice": "ellen",
  "file": "pc7_put_it_simply.mp3"
 },
 {
  "text": "Depend",
  "voice": "arthur",
  "file": "pc7_depend.mp3"
 },
 {
  "text": "That is a great question. Let me think.",
  "voice": "arthur",
  "file": "pc7_that_is_a_great_question_let_me_think.mp3"
 },
 {
  "text": "In other words, we choose the safer value.",
  "voice": "ellen",
  "file": "pc7_in_other_words_we_choose_the_safer_value.mp3"
 },
 {
  "text": "To be honest, it depends on the market.",
  "voice": "arthur",
  "file": "pc7_to_be_honest_it_depends_on_the_market.mp3"
 },
 {
  "text": "Roughly two weeks.",
  "voice": "ellen",
  "file": "pc7_roughly_two_weeks.mp3"
 },
 {
  "text": "Let me check and get back to you on that.",
  "voice": "arthur",
  "file": "pc7_let_me_check_and_get_back_to_you_on_that.mp3"
 },
 {
  "text": "Bear with me while I check the figure.",
  "voice": "ellen",
  "file": "pc7_bear_with_me_while_i_check_the_figure.mp3"
 }
]