[
 {
  "text": "Directness",
  "voice": "arthur",
  "file": "a15_directness.mp3"
 },
 {
  "text": "Rapport",
  "voice": "arthur",
  "file": "a15_rapport.mp3"
 },
 {
  "text": "Time zone",
  "voice": "arthur",
  "file": "a15_time_zone.mp3"
 },
 {
  "text": "Roadmap",
  "voice": "arthur",
  "file": "a15_roadmap.mp3"
 },
 {
  "text": "Release",
  "voice": "arthur",
  "file": "a15_release.mp3"
 },
 {
  "text": "Feature",
  "voice": "arthur",
  "file": "a15_feature.mp3"
 },
 {
  "text": "Feedback",
  "voice": "arthur",
  "file": "a15_feedback.mp3"
 },
 {
  "text": "Takeaway",
  "voice": "arthur",
  "file": "a15_takeaway.mp3"
 },
 {
  "text": "Align",
  "voice": "arthur",
  "file": "a15_align.mp3"
 },
 {
  "text": "Action item",
  "voice": "arthur",
  "file": "a15_action_item.mp3"
 },
 {
  "text": "Owner",
  "voice": "arthur",
  "file": "a15_owner.mp3"
 },
 {
  "text": "Circle back",
  "voice": "arthur",
  "file": "a15_circle_back.mp3"
 },
 {
  "text": "Could we go over the roadmap together?",
  "voice": "ellen",
  "file": "a15_could_we_go_over_the_roadmap_together.mp3"
 },
 {
  "text": "We are launching the new feature in May.",
  "voice": "arthur",
  "file": "a15_we_are_launching_the_new_feature_in_may.mp3"
 },
 {
  "text": "Perhaps it might be better to simplify the dashboard.",
  "voice": "ellen",
  "file": "a15_perhaps_it_might_be_better_to_simplify_the_dashb.mp3"
 },
 {
  "text": "Priya said she would book the training.",
  "voice": "arthur",
  "file": "a15_priya_said_she_would_book_the_training.mp3"
 },
 {
  "text": "Thanks for joining across the time zones, Patrícia. Could we go over the roadmap first?",
  "voice": "arthur",
  "file": "a15_thanks_for_joining_across_the_time_zones_patrici.mp3"
 },
 {
  "text": "Of course. So, we are launching the new feature in May, and the next release is on track.",
  "voice": "ellen",
  "file": "a15_of_course_so_we_are_launching_the_new_feature_in.mp3"
 },
 {
  "text": "Great. One piece of feedback: the client deck had a lot of detail.",
  "voice": "arthur",
  "file": "a15_great_one_piece_of_feedback_the_client_deck_had.mp3"
 },
 {
  "text": "That is a fair point. Perhaps it might be better to start with the big picture. My takeaway is to simplify it.",
  "voice": "ellen",
  "file": "a15_that_is_a_fair_point_perhaps_it_might_be_better.mp3"
 },
 {
  "text": "Perfect. And what did Priya say about the training?",
  "voice": "arthur",
  "file": "a15_perfect_and_what_did_priya_say_about_the_trainin.mp3"
 },
 {
  "text": "She said she would book it once the deck is ready. Let us align on the date and circle back by email.",
  "voice": "ellen",
  "file": "a15_she_said_she_would_book_it_once_the_deck_is_read.mp3"
 },
 {
  "text": "Hi Patrícia, this is David from the product team in San Francisco. I am leaving a quick note before our global sync tomorrow. Here is my plan for the call. First, I will walk the team through the roadmap, so everyone is aligned on the next release. We are launching the new reporting feature in May, and I am going to share the timeline for the rest of the quarter. I know the time zones are tricky, so I will keep my part short. One small piece of feedback from my side: the last deck had a lot of detail, and perhaps it might be better to start with the big picture. Could you bring the client's top requests to the sync? Let us circle back on the training dates after we agree on the roadmap. Thanks, and talk tomorrow.",
  "voice": "arthur",
  "file": "a15_listening_david.mp3"
 },
 {
  "text": "Hi Patrícia, it is Priya in Bangalore, just a short note before the product sync. I have read David's roadmap, and it looks good from my side. In our last call, the team said the new feature would ship in May, and that is still the plan. I want to build a little rapport with the new engineers, so I will start with a quick hello before we get into the details. One takeaway from the client feedback: they really like the new dashboard, but they asked for fewer clicks. I told them we would look at it, so it is now an action item, and I am the owner. The time zone overlap is small, so let us keep the sync focused. If we run out of time, we can circle back by email. See you on the call.",
  "voice": "ellen",
  "file": "a15_listening_priya.mp3"
 },
 {
  "text": "Directness",
  "voice": "arthur",
  "file": "pc15_directness.mp3"
 },
 {
  "text": "Rapport",
  "voice": "arthur",
  "file": "pc15_rapport.mp3"
 },
 {
  "text": "Time zone",
  "voice": "arthur",
  "file": "pc15_time_zone.mp3"
 },
 {
  "text": "Roadmap",
  "voice": "arthur",
  "file": "pc15_roadmap.mp3"
 },
 {
  "text": "Release",
  "voice": "arthur",
  "file": "pc15_release.mp3"
 },
 {
  "text": "Feature",
  "voice": "arthur",
  "file": "pc15_feature.mp3"
 },
 {
  "text": "Feedback",
  "voice": "arthur",
  "file": "pc15_feedback.mp3"
 },
 {
  "text": "Takeaway",
  "voice": "arthur",
  "file": "pc15_takeaway.mp3"
 },
 {
  "text": "Align",
  "voice": "arthur",
  "file": "pc15_align.mp3"
 },
 {
  "text": "Action item",
  "voice": "arthur",
  "file": "pc15_action_item.mp3"
 },
 {
  "text": "Owner",
  "voice": "arthur",
  "file": "pc15_owner.mp3"
 },
 {
  "text": "Circle back",
  "voice": "arthur",
  "file": "pc15_circle_back.mp3"
 },
 {
  "text": "Could we go over the roadmap together?",
  "voice": "ellen",
  "file": "pc15_could_we_go_over_the_roadmap_together.mp3"
 },
 {
  "text": "We are launching the new feature in May.",
  "voice": "arthur",
  "file": "pc15_we_are_launching_the_new_feature_in_may.mp3"
 },
 {
  "text": "I will share the timeline after the call.",
  "voice": "ellen",
  "file": "pc15_i_will_share_the_timeline_after_the_call.mp3"
 },
 {
  "text": "Perhaps it might be better to simplify the dashboard.",
  "voice": "arthur",
  "file": "pc15_perhaps_it_might_be_better_to_simplify_the_dashb.mp3"
 },
 {
  "text": "David said he would send the technical notes.",
  "voice": "ellen",
  "file": "pc15_david_said_he_would_send_the_technical_notes.mp3"
 },
 {
  "text": "Perhaps it might be better to simplify the deck.",
  "voice": "arthur",
  "file": "pc15_perhaps_it_might_be_better_to_simplify_the_deck.mp3"
 },
 {
  "text": "She said she would book the training.",
  "voice": "ellen",
  "file": "pc15_she_said_she_would_book_the_training.mp3"
 },
 {
  "text": "Let us align on the dates and circle back by email.",
  "voice": "arthur",
  "file": "pc15_let_us_align_on_the_dates_and_circle_back_by_ema.mp3"
 },
 {
  "text": "Could we go over the roadmap first?",
  "voice": "ellen",
  "file": "pc15_could_we_go_over_the_roadmap_first.mp3"
 },
 {
  "text": "Let us align and circle back by email.",
  "voice": "arthur",
  "file": "pc15_let_us_align_and_circle_back_by_email.mp3"
 }
]