[
 {
  "text": "You delivered the talk to a live audience. Now the same work must reach readers.",
  "voice": "ellen",
  "file": "a16_you_delivered_the_talk_to_a_live_audience_now_th.mp3"
 },
 {
  "text": "On the page, we do not say I think. We say the results suggest.",
  "voice": "arthur",
  "file": "a16_on_the_page_we_do_not_say_i_think_we_say_the_res.mp3"
 },
 {
  "text": "Synopsis",
  "voice": "arthur",
  "file": "a16_synopsis.mp3"
 },
 {
  "text": "Prediction",
  "voice": "arthur",
  "file": "a16_prediction.mp3"
 },
 {
  "text": "Results",
  "voice": "arthur",
  "file": "a16_results.mp3"
 },
 {
  "text": "Peer review",
  "voice": "arthur",
  "file": "a16_peer_review.mp3"
 },
 {
  "text": "Citation",
  "voice": "arthur",
  "file": "a16_citation.mp3"
 },
 {
  "text": "Manuscript",
  "voice": "arthur",
  "file": "a16_manuscript.mp3"
 },
 {
  "text": "Submission",
  "voice": "arthur",
  "file": "a16_submission.mp3"
 },
 {
  "text": "Journal",
  "voice": "arthur",
  "file": "a16_journal.mp3"
 },
 {
  "text": "Our hypothesis was that a higher dose would improve recovery.",
  "voice": "ellen",
  "file": "a16_our_hypothesis_was_that_a_higher_dose_would_impr.mp3"
 },
 {
  "text": "The findings have shown a clear effect, supported by each citation.",
  "voice": "arthur",
  "file": "a16_the_findings_have_shown_a_clear_effect_supported.mp3"
 },
 {
  "text": "After peer review, the manuscript was accepted by the journal.",
  "voice": "ellen",
  "file": "a16_after_peer_review_the_manuscript_was_accepted_by.mp3"
 },
 {
  "text": "We recruited ninety patients and measured their recovery.",
  "voice": "arthur",
  "file": "a16_we_recruited_ninety_patients_and_measured_their.mp3"
 },
 {
  "text": "The study has shown a strong association.",
  "voice": "ellen",
  "file": "a16_the_study_has_shown_a_strong_association.mp3"
 },
 {
  "text": "We analyzed the data over six months.",
  "voice": "arthur",
  "file": "a16_we_analyzed_the_data_over_six_months.mp3"
 },
 {
  "text": "We have found that the effect is significant.",
  "voice": "ellen",
  "file": "a16_we_have_found_that_the_effect_is_significant.mp3"
 },
 {
  "text": "Patricia, the manuscript looks great. Is the abstract ready for submission?",
  "voice": "arthur",
  "file": "a16_patricia_the_manuscript_looks_great_is_the_abstr.mp3"
 },
 {
  "text": "Almost. I am checking the tenses. The methods are in the past simple, and the findings are in the present perfect.",
  "voice": "ellen",
  "file": "a16_almost_i_am_checking_the_tenses_the_methods_are.mp3"
 },
 {
  "text": "Good. And the citations -- have you added the recent ones?",
  "voice": "arthur",
  "file": "a16_good_and_the_citations_have_you_added_the_recent.mp3"
 },
 {
  "text": "Yes. Every claim now has a citation. The study has shown the effect, and the references support it.",
  "voice": "ellen",
  "file": "a16_yes_every_claim_now_has_a_citation_the_study_has.mp3"
 },
 {
  "text": "Perfect. Which journal are we sending it to, and when does peer review start?",
  "voice": "arthur",
  "file": "a16_perfect_which_journal_are_we_sending_it_to_and_w.mp3"
 },
 {
  "text": "The leading clinical journal. Once I finish the abstract, I will send the submission, and peer review begins.",
  "voice": "ellen",
  "file": "a16_the_leading_clinical_journal_once_i_finish_the_a.mp3"
 },
 {
  "text": "The abstract sums up the aim, the methods and the findings.",
  "voice": "arthur",
  "file": "a16_the_abstract_sums_up_the_aim_the_methods_and_the.mp3"
 },
 {
  "text": "We measured recovery over six months.",
  "voice": "ellen",
  "file": "a16_we_measured_recovery_over_six_months.mp3"
 },
 {
  "text": "Every claim is backed by a citation.",
  "voice": "arthur",
  "file": "a16_every_claim_is_backed_by_a_citation.mp3"
 },
 {
  "text": "Good afternoon. Let me walk you through the abstract of our new manuscript before we submit it to the journal. An abstract is short, but it has a clear shape, and every sentence does one job. The first sentence gives the background and the gap: little is known about how the supplement affects recovery in older patients. The second sentence states the aim and the hypothesis: we predicted that a higher dose would lead to a better outcome. Then come the methods, written in the past simple, because they are finished: we recruited ninety patients, we measured their recovery over six months, and we analyzed the data. After the methods come the findings, and here the tense changes. We use the present perfect, because the findings are new and still matter today: the study has shown a strong association between the dose and recovery, and we have found that the effect is significant above a clear threshold. The final sentence gives the conclusion and why it matters: these results have implications for how the supplement is prescribed, and they support a larger trial. Notice the register. There is no I think and no maybe. We write we found, the data show, the results suggest. Every claim is careful, and every claim is backed by the findings. Once the abstract is clear, the rest of the paper, and the peer review, become much easier.",
  "voice": "ellen",
  "file": "a16_listening_abstract_walkthrough.mp3"
 },
 {
  "text": "Hi Patricia, this is the handling editor at the journal, calling about your submission. Good news first: the reviewers have read your manuscript and the response is positive. They describe the findings as solid and the writing as clear. I have two requests before we move forward. First, please check your tenses in the abstract. In a few places you have used the past simple for the findings, but our style asks for the present perfect there, because the findings still stand. So change we found a strong association to we have found a strong association. Keep the past simple for the methods, that part is correct. Second, the reviewers have asked for two more citations in the introduction, to show how your work builds on earlier research. Add those, and add the reference to the citation list at the end. One reviewer has also suggested a small change to the hypothesis sentence, to make the prediction sharper. I will send the full comments by email today. If you return the revised manuscript within three weeks, we should be able to confirm acceptance for the next issue. Congratulations again, Patricia. This is strong work, and we are glad to have it. Talk soon.",
  "voice": "arthur",
  "file": "a16_listening_editor_voicemail.mp3"
 },
 {
  "text": "First, give the background and the gap your study fills. Next, state the aim and the hypothesis you tested. After that, describe the methods in the past simple. Then, report the findings in the present perfect. Finally, give the conclusion and explain why it matters.",
  "voice": "arthur",
  "file": "pc16_order_abstract.mp3"
 },
 {
  "text": "Synopsis",
  "voice": "arthur",
  "file": "pc16_synopsis.mp3"
 },
 {
  "text": "Prediction",
  "voice": "arthur",
  "file": "pc16_prediction.mp3"
 },
 {
  "text": "Results",
  "voice": "arthur",
  "file": "pc16_results.mp3"
 },
 {
  "text": "Peer review",
  "voice": "arthur",
  "file": "pc16_peer_review.mp3"
 },
 {
  "text": "Citation",
  "voice": "arthur",
  "file": "pc16_citation.mp3"
 },
 {
  "text": "Manuscript",
  "voice": "arthur",
  "file": "pc16_manuscript.mp3"
 },
 {
  "text": "Submission",
  "voice": "arthur",
  "file": "pc16_submission.mp3"
 },
 {
  "text": "Journal",
  "voice": "arthur",
  "file": "pc16_journal.mp3"
 },
 {
  "text": "The synopsis sums up the whole study in one paragraph.",
  "voice": "ellen",
  "file": "pc16_the_synopsis_sums_up_the_whole_study_in_one_para.mp3"
 },
 {
  "text": "Our prediction was that a higher dose would improve recovery.",
  "voice": "arthur",
  "file": "pc16_our_prediction_was_that_a_higher_dose_would_impr.mp3"
 },
 {
  "text": "Each claim needs a citation to support it.",
  "voice": "ellen",
  "file": "pc16_each_claim_needs_a_citation_to_support_it.mp3"
 },
 {
  "text": "After peer review, the manuscript was accepted.",
  "voice": "arthur",
  "file": "pc16_after_peer_review_the_manuscript_was_accepted.mp3"
 },
 {
  "text": "We finished the manuscript and sent it to the journal.",
  "voice": "ellen",
  "file": "pc16_we_finished_the_manuscript_and_sent_it_to_the_jo.mp3"
 },
 {
  "text": "The paper was accepted by a leading medical journal.",
  "voice": "arthur",
  "file": "pc16_the_paper_was_accepted_by_a_leading_medical_jour.mp3"
 },
 {
  "text": "The abstract sums up the aim, the methods and the findings.",
  "voice": "ellen",
  "file": "pc16_the_abstract_sums_up_the_aim_the_methods_and_the.mp3"
 },
 {
  "text": "The study has shown a strong association.",
  "voice": "arthur",
  "file": "pc16_the_study_has_shown_a_strong_association.mp3"
 },
 {
  "text": "We measured recovery over six months.",
  "voice": "ellen",
  "file": "pc16_we_measured_recovery_over_six_months.mp3"
 },
 {
  "text": "After peer review, the manuscript was accepted by the journal.",
  "voice": "arthur",
  "file": "pc16_after_peer_review_the_manuscript_was_accepted_by.mp3"
 },
 {
  "text": "Every claim is backed by a citation.",
  "voice": "ellen",
  "file": "pc16_every_claim_is_backed_by_a_citation.mp3"
 }
]