[
 {
  "text": "Negotiate",
  "voice": "arthur",
  "file": "a4_negotiate.mp3"
 },
 {
  "text": "Supplier",
  "voice": "arthur",
  "file": "a4_supplier.mp3"
 },
 {
  "text": "Quote",
  "voice": "arthur",
  "file": "a4_quote.mp3"
 },
 {
  "text": "Proposal",
  "voice": "arthur",
  "file": "a4_proposal.mp3"
 },
 {
  "text": "Terms",
  "voice": "arthur",
  "file": "a4_terms.mp3"
 },
 {
  "text": "Discount",
  "voice": "arthur",
  "file": "a4_discount.mp3"
 },
 {
  "text": "Counteroffer",
  "voice": "arthur",
  "file": "a4_counteroffer.mp3"
 },
 {
  "text": "Agreement",
  "voice": "arthur",
  "file": "a4_agreement.mp3"
 },
 {
  "text": "Flexible",
  "voice": "arthur",
  "file": "a4_flexible.mp3"
 },
 {
  "text": "Commitment",
  "voice": "arthur",
  "file": "a4_commitment.mp3"
 },
 {
  "text": "Would you consider a discount?",
  "voice": "ellen",
  "file": "a4_would_you_consider_a_discount.mp3"
 },
 {
  "text": "Would you consider a discount for a longer deal?",
  "voice": "arthur",
  "file": "a4_would_you_consider_a_discount_for_a_longer_deal.mp3"
 },
 {
  "text": "We would accept these terms with full support.",
  "voice": "ellen",
  "file": "a4_we_would_accept_these_terms_with_full_support.mp3"
 },
 {
  "text": "I would suggest a two-year contract.",
  "voice": "arthur",
  "file": "a4_i_would_suggest_a_two_year_contract.mp3"
 },
 {
  "text": "That would work for both sides.",
  "voice": "ellen",
  "file": "a4_that_would_work_for_both_sides.mp3"
 },
 {
  "text": "Thanks for your interest, Rafael. As you saw, the quote for one year is twelve thousand dollars.",
  "voice": "ellen",
  "file": "a4_thanks_for_your_interest_rafael_as_you_saw_the_q.mp3"
 },
 {
  "text": "Thank you, Sofia. The proposal looks good, but the price is a little over our budget this year.",
  "voice": "arthur",
  "file": "a4_thank_you_sofia_the_proposal_looks_good_but_the.mp3"
 },
 {
  "text": "I understand. What did you have in mind?",
  "voice": "ellen",
  "file": "a4_i_understand_what_did_you_have_in_mind.mp3"
 },
 {
  "text": "Would you consider a discount for a two-year commitment instead of one?",
  "voice": "arthur",
  "file": "a4_would_you_consider_a_discount_for_a_two_year_com.mp3"
 },
 {
  "text": "For a two-year commitment, I could offer ten percent off, but I would need faster payment.",
  "voice": "ellen",
  "file": "a4_for_a_two_year_commitment_i_could_offer_ten_perc.mp3"
 },
 {
  "text": "That would work. We would accept the longer term and faster payment, but only with support included.",
  "voice": "arthur",
  "file": "a4_that_would_work_we_would_accept_the_longer_term.mp3"
 },
 {
  "text": "Hi, this is Rafael with a quick update after my call with the software supplier, before our budget meeting. The good news is that we have a deal, and it is a better one than the first quote. You remember the problem: their opening price was about fifteen percent over our budget for this year, so I could not just accept it. I went into the call with a clear plan. I knew which terms mattered most to us, and I knew the one number I would be happy with. On the call I stayed polite. I thanked them for the proposal, but I was honest that the price was too high. Then I asked the key question: would they consider a discount for a longer commitment? They were flexible. They offered ten percent off if we signed for two years instead of one, but in return they wanted faster payment. So I made a counteroffer. I said we would accept the two-year term and the faster payment, but only if full support was included at no extra cost. After a few minutes, we reached an agreement that works for both sides. We get a better price and full support; they get a longer deal. I will send the new quote and the terms around before the meeting. Thanks.",
  "voice": "arthur",
  "file": "a4_listening_rafael_recap.mp3"
 },
 {
  "text": "Hello Rafael, this is Sofia from the vendor team, following up on our call with a revised offer in writing, as you asked. Thank you again for a friendly and professional conversation. Here is where we have landed. On the price, we are happy to give you the ten percent discount we discussed, in exchange for the two-year commitment. On payment, we would still like the faster thirty-day terms, and I can see from our notes that you are comfortable with that. And on your main request, yes, we agree: full technical support is now included at no extra cost for the whole length of the contract. So, to recap the agreement: a two-year deal, ten percent off the original quote, thirty-day payment, and support included. I think that is a fair result for both sides. I will put all of this into a formal proposal and send it over for signature this week. If anything looks different from what you expected, just give me a call and we will sort it out. Looking forward to working with your team. Thanks, Rafael.",
  "voice": "ellen",
  "file": "a4_listening_sofia_offer.mp3"
 },
 {
  "text": "Negotiate",
  "voice": "arthur",
  "file": "pc4_negotiate.mp3"
 },
 {
  "text": "Supplier",
  "voice": "arthur",
  "file": "pc4_supplier.mp3"
 },
 {
  "text": "Quote",
  "voice": "arthur",
  "file": "pc4_quote.mp3"
 },
 {
  "text": "Proposal",
  "voice": "arthur",
  "file": "pc4_proposal.mp3"
 },
 {
  "text": "Terms",
  "voice": "arthur",
  "file": "pc4_terms.mp3"
 },
 {
  "text": "Discount",
  "voice": "arthur",
  "file": "pc4_discount.mp3"
 },
 {
  "text": "Counteroffer",
  "voice": "arthur",
  "file": "pc4_counteroffer.mp3"
 },
 {
  "text": "Agreement",
  "voice": "arthur",
  "file": "pc4_agreement.mp3"
 },
 {
  "text": "Flexible",
  "voice": "arthur",
  "file": "pc4_flexible.mp3"
 },
 {
  "text": "Commitment",
  "voice": "arthur",
  "file": "pc4_commitment.mp3"
 },
 {
  "text": "Would you consider a discount for a longer deal?",
  "voice": "ellen",
  "file": "pc4_would_you_consider_a_discount_for_a_longer_deal.mp3"
 },
 {
  "text": "We would accept the terms with full support.",
  "voice": "arthur",
  "file": "pc4_we_would_accept_the_terms_with_full_support.mp3"
 },
 {
  "text": "The first quote is over our budget.",
  "voice": "ellen",
  "file": "pc4_the_first_quote_is_over_our_budget.mp3"
 },
 {
  "text": "I made a counteroffer with support included.",
  "voice": "arthur",
  "file": "pc4_i_made_a_counteroffer_with_support_included.mp3"
 },
 {
  "text": "We reached an agreement that works for both sides.",
  "voice": "ellen",
  "file": "pc4_we_reached_an_agreement_that_works_for_both_side.mp3"
 },
 {
  "text": "We would accept the terms with support included.",
  "voice": "arthur",
  "file": "pc4_we_would_accept_the_terms_with_support_included.mp3"
 },
 {
  "text": "The first quote is a little over our budget this year.",
  "voice": "ellen",
  "file": "pc4_the_first_quote_is_a_little_over_our_budget_this.mp3"
 },
 {
  "text": "I would suggest a two-year commitment.",
  "voice": "arthur",
  "file": "pc4_i_would_suggest_a_two_year_commitment.mp3"
 },
 {
  "text": "Thank you for the proposal, but the price is a little high.",
  "voice": "ellen",
  "file": "pc4_thank_you_for_the_proposal_but_the_price_is_a_li.mp3"
 },
 {
  "text": "Would you consider a discount for a longer commitment?",
  "voice": "arthur",
  "file": "pc4_would_you_consider_a_discount_for_a_longer_commi.mp3"
 },
 {
  "text": "We would accept faster payment if support is included.",
  "voice": "ellen",
  "file": "pc4_we_would_accept_faster_payment_if_support_is_inc.mp3"
 },
 {
  "text": "That would work. Let me make a small counteroffer.",
  "voice": "arthur",
  "file": "pc4_that_would_work_let_me_make_a_small_counteroffer.mp3"
 },
 {
  "text": "Great, I think we have an agreement.",
  "voice": "ellen",
  "file": "pc4_great_i_think_we_have_an_agreement.mp3"
 }
]