[
 {
  "text": "Specialize in",
  "voice": "arthur",
  "file": "a1_specialize_in.mp3"
 },
 {
  "text": "Background",
  "voice": "arthur",
  "file": "a1_background.mp3"
 },
 {
  "text": "Expertise",
  "voice": "arthur",
  "file": "a1_expertise.mp3"
 },
 {
  "text": "Reproductive medicine",
  "voice": "arthur",
  "file": "a1_reproductive_medicine.mp3"
 },
 {
  "text": "Fertility",
  "voice": "arthur",
  "file": "a1_fertility.mp3"
 },
 {
  "text": "Clinical",
  "voice": "arthur",
  "file": "a1_clinical.mp3"
 },
 {
  "text": "Procedure",
  "voice": "arthur",
  "file": "a1_procedure.mp3"
 },
 {
  "text": "Hands-on",
  "voice": "arthur",
  "file": "a1_hands_on.mp3"
 },
 {
  "text": "Track record",
  "voice": "arthur",
  "file": "a1_track_record.mp3"
 },
 {
  "text": "Residency",
  "voice": "arthur",
  "file": "a1_residency.mp3"
 },
 {
  "text": "Peer-reviewed",
  "voice": "arthur",
  "file": "a1_peer_reviewed.mp3"
 },
 {
  "text": "Fluent",
  "voice": "arthur",
  "file": "a1_fluent.mp3"
 },
 {
  "text": "Reproductive",
  "voice": "arthur",
  "file": "a1_reproductive.mp3"
 },
 {
  "text": "I work as a gynecologist in São Paulo.",
  "voice": "ellen",
  "file": "a1_i_work_as_a_gynecologist_in_sao_paulo.mp3"
 },
 {
  "text": "I have been working in reproductive medicine for eight years.",
  "voice": "arthur",
  "file": "a1_i_have_been_working_in_reproductive_medicine_for.mp3"
 },
 {
  "text": "I completed my residency in 2015.",
  "voice": "ellen",
  "file": "a1_i_completed_my_residency_in_2015.mp3"
 },
 {
  "text": "I have built a strong track record with fertility patients.",
  "voice": "arthur",
  "file": "a1_i_have_built_a_strong_track_record_with_fertilit.mp3"
 },
 {
  "text": "Hi, I do not think we have met. I am Mark, from Chicago. And you are?",
  "voice": "arthur",
  "file": "a1_hi_i_do_not_think_we_have_met_i_am_mark_from_chi.mp3"
 },
 {
  "text": "Hi Mark, I am Eliane. I am a doctor from São Paulo, in Brazil.",
  "voice": "ellen",
  "file": "a1_hi_mark_i_am_eliane_i_am_a_doctor_from_sao_paulo.mp3"
 },
 {
  "text": "Nice to meet you, Eliane. So, what do you do back in Brazil?",
  "voice": "arthur",
  "file": "a1_nice_to_meet_you_eliane_so_what_do_you_do_back_i.mp3"
 },
 {
  "text": "I work as a gynecologist, and I specialize in reproductive medicine.",
  "voice": "ellen",
  "file": "a1_i_work_as_a_gynecologist_and_i_specialize_in_rep.mp3"
 },
 {
  "text": "That sounds fascinating. How long have you been doing that?",
  "voice": "arthur",
  "file": "a1_that_sounds_fascinating_how_long_have_you_been_d.mp3"
 },
 {
  "text": "I have been working in fertility care for about eight years now.",
  "voice": "ellen",
  "file": "a1_i_have_been_working_in_fertility_care_for_about.mp3"
 },
 {
  "text": "Impressive. And are you working on anything new at the moment?",
  "voice": "arthur",
  "file": "a1_impressive_and_are_you_working_on_anything_new_a.mp3"
 },
 {
  "text": "Yes, actually. I am opening my own clinic next year, with American technology.",
  "voice": "ellen",
  "file": "a1_yes_actually_i_am_opening_my_own_clinic_next_yea.mp3"
 },
 {
  "text": "That is a big step. I would love to hear more about it over dinner.",
  "voice": "arthur",
  "file": "a1_that_is_a_big_step_i_would_love_to_hear_more_abo.mp3"
 },
 {
  "text": "My background is in gynecology, and I completed my residency in 2015.",
  "voice": "arthur",
  "file": "a1_my_background_is_in_gynecology_and_i_completed_m.mp3"
 },
 {
  "text": "Right now, I am opening my own fertility clinic.",
  "voice": "ellen",
  "file": "a1_right_now_i_am_opening_my_own_fertility_clinic.mp3"
 },
 {
  "text": "Good evening, everyone, and welcome to the opening session of our executive education program. My name is Mark, and I will be your program coordinator this week. Over the next few days, you will meet leaders from more than twenty countries, from medicine, technology, and finance. Tonight is simple: we just want you to relax and connect. In a few minutes, I will ask each of you to introduce yourself in one minute. Please tell us your name, where you are from, what you do, and one project you are working on right now. Do not worry about perfect grammar. We care about your story, not your accent. So take a breath, and let us begin.",
  "voice": "arthur",
  "file": "a1_listening_orientation.mp3"
 },
 {
  "text": "Hi Eliane, it's Dr. Sofia Reyes calling from New York. It has been a long time since your months here at the medical center, and I was thinking about you today. I heard that you have been building something new in reproductive medicine back in Brazil, and I would love to hear more. We are organizing a small case discussion next month, and I immediately thought of your work with fertility patients. I know your English is a little rusty, but honestly, mine was too when I started, and it comes back faster than you think. Give me a call when you have a moment. It would be wonderful to reconnect. Take care, and talk soon.",
  "voice": "ellen",
  "file": "a1_listening_voicemail.mp3"
 },
 {
  "text": "Specialize in",
  "voice": "arthur",
  "file": "pc_specialize_in.mp3"
 },
 {
  "text": "Background",
  "voice": "arthur",
  "file": "pc_background.mp3"
 },
 {
  "text": "Expertise",
  "voice": "arthur",
  "file": "pc_expertise.mp3"
 },
 {
  "text": "Reproductive medicine",
  "voice": "arthur",
  "file": "pc_reproductive_medicine.mp3"
 },
 {
  "text": "Fertility",
  "voice": "arthur",
  "file": "pc_fertility.mp3"
 },
 {
  "text": "Clinical",
  "voice": "arthur",
  "file": "pc_clinical.mp3"
 },
 {
  "text": "Procedure",
  "voice": "arthur",
  "file": "pc_procedure.mp3"
 },
 {
  "text": "Hands-on",
  "voice": "arthur",
  "file": "pc_hands_on.mp3"
 },
 {
  "text": "Track record",
  "voice": "arthur",
  "file": "pc_track_record.mp3"
 },
 {
  "text": "Residency",
  "voice": "arthur",
  "file": "pc_residency.mp3"
 },
 {
  "text": "Peer-reviewed",
  "voice": "arthur",
  "file": "pc_peer_reviewed.mp3"
 },
 {
  "text": "Fluent",
  "voice": "arthur",
  "file": "pc_fluent.mp3"
 },
 {
  "text": "I have been working in fertility care for eight years.",
  "voice": "ellen",
  "file": "pc_i_have_been_working_in_fertility_care_for_eight.mp3"
 },
 {
  "text": "I have worked in reproductive medicine since 2016.",
  "voice": "arthur",
  "file": "pc_i_have_worked_in_reproductive_medicine_since_201.mp3"
 },
 {
  "text": "I completed my residency in 2015.",
  "voice": "ellen",
  "file": "pc_i_completed_my_residency_in_2015.mp3"
 },
 {
  "text": "I specialize in reproductive medicine.",
  "voice": "arthur",
  "file": "pc_i_specialize_in_reproductive_medicine.mp3"
 },
 {
  "text": "I have built a strong track record with my patients.",
  "voice": "ellen",
  "file": "pc_i_have_built_a_strong_track_record_with_my_patie.mp3"
 },
 {
  "text": "I work as a gynecologist in São Paulo.",
  "voice": "arthur",
  "file": "pc_i_work_as_a_gynecologist_in_sao_paulo.mp3"
 },
 {
  "text": "I work as a gynecologist, and I specialize in reproductive medicine.",
  "voice": "ellen",
  "file": "pc_i_work_as_a_gynecologist_and_i_specialize_in_rep.mp3"
 },
 {
  "text": "I have been working in fertility care for about eight years.",
  "voice": "arthur",
  "file": "pc_i_have_been_working_in_fertility_care_for_about.mp3"
 },
 {
  "text": "My background is in gynecology, and I completed my residency in 2015.",
  "voice": "ellen",
  "file": "pc_my_background_is_in_gynecology_and_i_completed_m.mp3"
 },
 {
  "text": "I have built a strong track record with my fertility patients.",
  "voice": "arthur",
  "file": "pc_i_have_built_a_strong_track_record_with_my_ferti.mp3"
 },
 {
  "text": "What do you specialize in, and how long have you been doing it?",
  "voice": "ellen",
  "file": "pc_what_do_you_specialize_in_and_how_long_have_you.mp3"
 },
 {
  "text": "Right now, I am opening my own fertility clinic.",
  "voice": "arthur",
  "file": "pc_right_now_i_am_opening_my_own_fertility_clinic.mp3"
 }
]