[
 {
  "text": "The metrics have been moving against the baseline, and four of five are on track.",
  "voice": "ellen",
  "file": "a14_the_metrics_have_been_moving_against_the_baselin.mp3"
 },
 {
  "text": "The change works. Now the board asks: which investment delivers the most value?",
  "voice": "arthur",
  "file": "a14_the_change_works_now_the_board_asks_which_invest.mp3"
 },
 {
  "text": "ROI",
  "voice": "arthur",
  "file": "a14_roi.mp3"
 },
 {
  "text": "Payback",
  "voice": "arthur",
  "file": "a14_payback.mp3"
 },
 {
  "text": "Upfront Cost",
  "voice": "arthur",
  "file": "a14_upfront_cost.mp3"
 },
 {
  "text": "Scalable",
  "voice": "arthur",
  "file": "a14_scalable.mp3"
 },
 {
  "text": "Cost-effective",
  "voice": "arthur",
  "file": "a14_cost_effective.mp3"
 },
 {
  "text": "Feasible",
  "voice": "arthur",
  "file": "a14_feasible.mp3"
 },
 {
  "text": "Allocate",
  "voice": "arthur",
  "file": "a14_allocate.mp3"
 },
 {
  "text": "Downside",
  "voice": "arthur",
  "file": "a14_downside.mp3"
 },
 {
  "text": "Building is cheaper than buying at the start.",
  "voice": "ellen",
  "file": "a14_building_is_cheaper_than_buying_at_the_start.mp3"
 },
 {
  "text": "Buying is more cost-effective than building over three years.",
  "voice": "arthur",
  "file": "a14_buying_is_more_cost_effective_than_building_over.mp3"
 },
 {
  "text": "The vendor option has the highest return.",
  "voice": "ellen",
  "file": "a14_the_vendor_option_has_the_highest_return.mp3"
 },
 {
  "text": "Buying is the most scalable option of the two.",
  "voice": "arthur",
  "file": "a14_buying_is_the_most_scalable_option_of_the_two.mp3"
 },
 {
  "text": "My recommendation is to buy. The ROI is the highest of the two options, and the payback is quicker.",
  "voice": "arthur",
  "file": "a14_my_recommendation_is_to_buy_the_roi_is_the_highe.mp3"
 },
 {
  "text": "But buying has the higher upfront cost. Why not build, if it is cheaper?",
  "voice": "ellen",
  "file": "a14_but_buying_has_the_higher_upfront_cost_why_not_b.mp3"
 },
 {
  "text": "Building is cheaper to start, but buying is more cost-effective over three years. It is also more scalable.",
  "voice": "arthur",
  "file": "a14_building_is_cheaper_to_start_but_buying_is_more.mp3"
 },
 {
  "text": "And the downside of buying? I do not want only the good side.",
  "voice": "ellen",
  "file": "a14_and_the_downside_of_buying_i_do_not_want_only_th.mp3"
 },
 {
  "text": "The downside is the price tag. But it is the most feasible path, so we should allocate the budget to buy.",
  "voice": "arthur",
  "file": "a14_the_downside_is_the_price_tag_but_it_is_the_most.mp3"
 },
 {
  "text": "Good. Show me the payback as one number, and send me the updated business case by Wednesday.",
  "voice": "ellen",
  "file": "a14_good_show_me_the_payback_as_one_number_and_send.mp3"
 },
 {
  "text": "The downside is the upfront cost, but the payback is quicker.",
  "voice": "ellen",
  "file": "a14_the_downside_is_the_upfront_cost_but_the_payback.mp3"
 },
 {
  "text": "We should allocate the budget to the most cost-effective option.",
  "voice": "arthur",
  "file": "a14_we_should_allocate_the_budget_to_the_most_cost_e.mp3"
 },
 {
  "text": "Carlos, before the board asks you to justify the spend, let me brief you on the two options for the next phase. Option one is to build the platform in-house. The upfront cost is lower, and it is more flexible than a vendor product, because the team can shape it. But the payback period is longer, the lead time is the biggest risk, and it is harder to scale. Option two is to buy from the vendor. It is more expensive upfront, but it is faster, it is more scalable, and the return on investment is higher over three years, because the payback is quicker. So the honest comparison is this: building is cheaper to start but slower to pay back; buying costs more now but delivers the most value over the cycle. The downside of building is the time; the downside of buying is the price tag the board will see first. My advice: lead with the option that is the most cost-effective over three years, not the one that is the cheapest on day one. Show the numbers side by side, name the trade-off, and recommend the one that is more viable for where we want to be. Boards approve the spend when the case is clear, not when it is loud.",
  "voice": "arthur",
  "file": "a14_listening1_advisor_options_brief.mp3"
 },
 {
  "text": "Hi Carlos, this is Diana, with a quick recap after the investment review. The directors liked the way you made the case. You compared the two options side by side, you were clear that buying is more expensive upfront but more cost-effective over three years, and you did not hide the downside of either path, which they respected. A few notes for next time. First, the payback period: that was your strongest number, so lead with it, because a shorter payback is the most persuasive point for this board. Second, scalability: you said the vendor option is more scalable, but the board wanted proof, so bring one concrete example of how it scales. Third, the upfront cost: do not apologize for it; frame it as the price of the higher return. One thing to add: a single slide that shows the return on investment of each option as one clear number, because the board decides faster when the comparison is one line, not ten. Send me the updated business case by Wednesday, and we will walk the lead director through it before the vote. Strong work, Carlos. You made the more expensive option sound like the smarter one, and that is exactly the case we needed. Talk soon.",
  "voice": "ellen",
  "file": "a14_listening2_diana_decision_recap.mp3"
 },
 {
  "text": "ROI",
  "voice": "arthur",
  "file": "pc14_roi.mp3"
 },
 {
  "text": "Payback",
  "voice": "arthur",
  "file": "pc14_payback.mp3"
 },
 {
  "text": "Upfront Cost",
  "voice": "arthur",
  "file": "pc14_upfront_cost.mp3"
 },
 {
  "text": "Scalable",
  "voice": "arthur",
  "file": "pc14_scalable.mp3"
 },
 {
  "text": "Cost-effective",
  "voice": "arthur",
  "file": "pc14_cost_effective.mp3"
 },
 {
  "text": "Feasible",
  "voice": "arthur",
  "file": "pc14_feasible.mp3"
 },
 {
  "text": "Allocate",
  "voice": "arthur",
  "file": "pc14_allocate.mp3"
 },
 {
  "text": "Downside",
  "voice": "arthur",
  "file": "pc14_downside.mp3"
 },
 {
  "text": "Building is cheaper than buying at the start.",
  "voice": "ellen",
  "file": "pc14_building_is_cheaper_than_buying_at_the_start.mp3"
 },
 {
  "text": "Buying is more cost-effective than building.",
  "voice": "arthur",
  "file": "pc14_buying_is_more_cost_effective_than_building.mp3"
 },
 {
  "text": "The vendor option has the highest return.",
  "voice": "ellen",
  "file": "pc14_the_vendor_option_has_the_highest_return.mp3"
 },
 {
  "text": "Buying is the most scalable option.",
  "voice": "arthur",
  "file": "pc14_buying_is_the_most_scalable_option.mp3"
 },
 {
  "text": "The money you pay at the start is the upfront cost.",
  "voice": "ellen",
  "file": "pc14_the_money_you_pay_at_the_start_is_the_upfront_co.mp3"
 },
 {
  "text": "We should allocate the budget to the most cost-effective option.",
  "voice": "arthur",
  "file": "pc14_we_should_allocate_the_budget_to_the_most_cost_e.mp3"
 },
 {
  "text": "First, state the recommendation. Then compare the two options side by side. Next, lead with the strongest number, the payback. After that, name the downside of each option honestly. Finally, ask the board to allocate the budget.",
  "voice": "ellen",
  "file": "pc14_first_state_the_recommendation_then_compare_the.mp3"
 },
 {
  "text": "Buying is more cost-effective than building over three years.",
  "voice": "arthur",
  "file": "pc14_buying_is_more_cost_effective_than_building_over.mp3"
 },
 {
  "text": "The downside is the upfront cost, but the payback is quicker.",
  "voice": "ellen",
  "file": "pc14_the_downside_is_the_upfront_cost_but_the_payback.mp3"
 }
]